pygmtsar/ASF.py
pygmtsar/AWS.py
pygmtsar/GMT.py
pygmtsar/IO.py
pygmtsar/MultiInstanceManager.py
pygmtsar/NCubeVTK.py
pygmtsar/PRM.py
pygmtsar/PRM_gmtsar.py
pygmtsar/S1.py
pygmtsar/Stack.py
pygmtsar/Stack_align.py
pygmtsar/Stack_base.py
pygmtsar/Stack_dem.py
pygmtsar/Stack_detrend.py
pygmtsar/Stack_export.py
pygmtsar/Stack_geocode.py
pygmtsar/Stack_incidence.py
pygmtsar/Stack_landmask.py
pygmtsar/Stack_lstsq.py
pygmtsar/Stack_multilooking.py
pygmtsar/Stack_orbits.py
pygmtsar/Stack_phasediff.py
pygmtsar/Stack_prm.py
pygmtsar/Stack_ps.py
pygmtsar/Stack_reframe.py
pygmtsar/Stack_reframe_gmtsar.py
pygmtsar/Stack_sbas.py
pygmtsar/Stack_stl.py
pygmtsar/Stack_tidal.py
pygmtsar/Stack_topo.py
pygmtsar/Stack_trans.py
pygmtsar/Stack_trans_inv.py
pygmtsar/Stack_unwrap.py
pygmtsar/Stack_unwrap_snaphu.py
pygmtsar/Tiles.py
pygmtsar/XYZTiles.py
pygmtsar/__init__.py
pygmtsar/datagrid.py
pygmtsar/tqdm_dask.py
pygmtsar/tqdm_joblib.py
pygmtsar/utils.py
pygmtsar/data/geoid_egm96_icgem.grd
pygmtsar/data/google_colab.sh
pygmtsar-2025.4.8.post1.dist-info/licenses/LICENSE.txt
pygmtsar-2025.4.8.post1.dist-info/METADATA
pygmtsar-2025.4.8.post1.dist-info/WHEEL
pygmtsar-2025.4.8.post1.dist-info/top_level.txt
pygmtsar-2025.4.8.post1.dist-info/RECORD
