Metadata-Version: 2.4
Name: pygmtsar
Version: 2025.4.8.post1
Summary: PyGMTSAR (Python GMTSAR): Powerful and Accessible Satellite Interferometry
Home-page: https://github.com/AlexeyPechnikov/pygmtsar
Author: Alexey Pechnikov
Author-email: alexey@pechnikov.dev
License: BSD-3-Clause
Keywords: satellite interferometry,InSAR,remote sensing,geospatial analysis,Sentinel-1,SBAS,PSI
Classifier: Development Status :: 4 - Beta
Classifier: Intended Audience :: Science/Research
Classifier: Natural Language :: English
Classifier: License :: OSI Approved :: BSD License
Classifier: Operating System :: POSIX
Classifier: Operating System :: POSIX :: Linux
Classifier: Operating System :: MacOS
Classifier: Programming Language :: Python
Classifier: Programming Language :: Python :: 3.10
Classifier: Programming Language :: Python :: 3.11
Requires-Python: >=3.10
License-File: LICENSE.txt
Requires-Dist: xarray>=2024.1.0
Requires-Dist: numpy
Requires-Dist: numba
Requires-Dist: pandas>=2.2
Requires-Dist: geopandas
Requires-Dist: distributed>=2024.1.0
Requires-Dist: dask[complete]>=2024.4.1
Requires-Dist: opencv-python
Requires-Dist: joblib
Requires-Dist: tqdm
Requires-Dist: scipy
Requires-Dist: xgboost
Requires-Dist: cffi
Requires-Dist: shapely>=2.0.2
Requires-Dist: scikit-learn
Requires-Dist: xmltodict
Requires-Dist: rioxarray
Requires-Dist: tifffile
Requires-Dist: ipywidgets
Requires-Dist: h5netcdf>=1.3.0
Requires-Dist: h5py
Requires-Dist: nc-time-axis
Requires-Dist: statsmodels>=0.14.0
Requires-Dist: remotezip
Requires-Dist: asf_search
Requires-Dist: imageio
Requires-Dist: matplotlib
Requires-Dist: adjustText
Requires-Dist: seaborn
Dynamic: author
Dynamic: author-email
Dynamic: classifier
Dynamic: description
Dynamic: description-content-type
Dynamic: home-page
Dynamic: keywords
Dynamic: license
Dynamic: license-file
Dynamic: requires-dist
Dynamic: requires-python
Dynamic: summary
